[
  {"id": "1", "name": "White", "rgb": [255, 255, 255]},
  {"id": "2", "name": "Light Grey", "rgb": [196, 197, 204]},
  {"id": "3", "name": "Stone", "rgb": [149, 152, 159]},
  {"id": "4", "name": "Pewter", "rgb": [111, 117, 122]},
  {"id": "5", "name": "Grey", "rgb": [95, 96, 98]},
  {"id": "6", "name": "Charcoal", "rgb": [65, 67, 69]},
  {"id": "7", "name": "Dark Grey", "rgb": [54, 55, 56]},
  {"id": "8", "name": "Black", "rgb": [0, 0, 0]},
  {"id": "9", "name": "Peach", "rgb": [251, 202, 184]},
  {"id": "10", "name": "Flamingo", "rgb": [255, 171, 155]},
  {"id": "11", "name": "Blush", "rgb": [255, 136, 134]},
  {"id": "12", "name": "Salmon", "rgb": [255, 107, 114]},
  {"id": "13", "name": "Red", "rgb": [209, 32, 47]},
  {"id": "14", "name": "Cherry", "rgb": [170, 24, 44]},
  {"id": "15", "name": "Cranapple", "rgb": [130, 21, 31]},
  {"id": "16", "name": "Light Pink", "rgb": [255, 202, 218]},
  {"id": "17", "name": "Cotton Candy", "rgb": [255, 171, 204]},
  {"id": "18", "name": "Bubblegum", "rgb": [244, 107, 157]},
  {"id": "19", "name": "Rose", "rgb": [231, 63, 122]},
  {"id": "20", "name": "Pink", "rgb": [236, 55, 104]},
  {"id": "21", "name": "Magenta", "rgb": [214, 28, 89]},
  {"id": "22", "name": "Fruit Punch", "rgb": [195, 27, 77]},
  {"id": "23", "name": "Raspberry", "rgb": [158, 22, 63]},
  {"id": "24", "name": "Orchid", "rgb": [197, 111, 180]},
  {"id": "25", "name": "Fuchsia", "rgb": [181, 65, 152]},
  {"id": "26", "name": "Plum", "rgb": [154, 43, 125]},
  {"id": "27", "name": "Eggplant", "rgb": [95, 29, 93]},
  {"id": "28", "name": "Mulberry", "rgb": [71, 21, 61]},
  {"id": "29", "name": "Creme", "rgb": [242, 230, 180]},
  {"id": "30", "name": "Pastel Yellow", "rgb": [253, 244, 136]},
  {"id": "31", "name": "Yellow", "rgb": [253, 224, 8]},
  {"id": "32", "name": "Cheddar", "rgb": [253, 184, 21]},
  {"id": "33", "name": "Honey", "rgb": [231, 158, 34]},
  {"id": "34", "name": "Butterscotch", "rgb": [214, 136, 46]},
  {"id": "35", "name": "Orange Creme", "rgb": [251, 191, 133]},
  {"id": "36", "name": "Apricot", "rgb": [252, 160, 86]},
  {"id": "37", "name": "Orange", "rgb": [255, 112, 38]},
  {"id": "38", "name": "Hot Coral", "rgb": [255, 75, 62]},
  {"id": "39", "name": "Tomato", "rgb": [232, 57, 41]},
  {"id": "40", "name": "Tangerine", "rgb": [216, 76, 38]},
  {"id": "41", "name": "Spice", "rgb": [175, 62, 40]},
  {"id": "42", "name": "Rust", "rgb": [141, 48, 32]},
  {"id": "43", "name": "Robin's Egg", "rgb": [178, 227, 232]},
  {"id": "44", "name": "Toothpaste", "rgb": [137, 205, 216]},
  {"id": "45", "name": "Sky", "rgb": [66, 176, 213]},
  {"id": "46", "name": "Turquoise", "rgb": [0, 139, 186]},
  {"id": "47", "name": "Pastel Blue", "rgb": [93, 153, 212]},
  {"id": "48", "name": "Light Blue", "rgb": [43, 118, 192]},
  {"id": "49", "name": "Cobalt", "rgb": [0, 87, 167]},
  {"id": "50", "name": "Dark Blue", "rgb": [25, 43, 105]},
  {"id": "51", "name": "Midnight", "rgb": [21, 25, 68]},
  {"id": "52", "name": "Mist", "rgb": [194, 203, 224]},
  {"id": "53", "name": "Blueberry Creme", "rgb": [141, 163, 212]},
  {"id": "54", "name": "Periwinkle", "rgb": [92, 114, 170]},
  {"id": "55", "name": "Slate Blue", "rgb": [63, 88, 130]},
  {"id": "56", "name": "Denim", "rgb": [43, 67, 104]},
  {"id": "57", "name": "Light Lavender", "rgb": [201, 182, 224]},
  {"id": "58", "name": "Thistle", "rgb": [163, 131, 193]},
  {"id": "59", "name": "Pastel Lavender", "rgb": [146, 106, 167]},
  {"id": "60", "name": "Purple", "rgb": [100, 56, 139]},
  {"id": "61", "name": "Iris", "rgb": [71, 47, 115]},
  {"id": "62", "name": "Grape", "rgb": [50, 33, 84]},
  {"id": "63", "name": "GITD Green", "rgb": [216, 235, 184]},
  {"id": "64", "name": "Sherbet", "rgb": [205, 223, 100]},
  {"id": "65", "name": "Prickly Pear", "rgb": [195, 214, 45]},
  {"id": "66", "name": "Slime", "rgb": [154, 202, 51]},
  {"id": "67", "name": "Sage", "rgb": [145, 179, 103]},
  {"id": "68", "name": "Fern", "rgb": [107, 147, 70]},
  {"id": "69", "name": "Olive", "rgb": [82, 99, 48]},
  {"id": "70", "name": "Sour Apple", "rgb": [147, 214, 97]},
  {"id": "71", "name": "Pastel Green", "rgb": [97, 197, 86]},
  {"id": "72", "name": "Kiwi Lime", "rgb": [76, 184, 63]},
  {"id": "73", "name": "Bright Green", "rgb": [0, 169, 64]},
  {"id": "74", "name": "Shamrock", "rgb": [0, 134, 57]},
  {"id": "75", "name": "Dark Green", "rgb": [16, 93, 52]},
  {"id": "76", "name": "Evergreen", "rgb": [11, 60, 45]},
  {"id": "77", "name": "Mint", "rgb": [129, 211, 175]},
  {"id": "78", "name": "Light Green", "rgb": [55, 198, 159]},
  {"id": "79", "name": "Lagoon", "rgb": [0, 165, 149]},
  {"id": "80", "name": "Parrot Green", "rgb": [0, 128, 117]},
  {"id": "81", "name": "Teal", "rgb": [0, 99, 92]},
  {"id": "82", "name": "Forest", "rgb": [25, 60, 53]},
  {"id": "83", "name": "Dark Spruce", "rgb": [15, 39, 30]},
  {"id": "84", "name": "Toasted Marshmallow", "rgb": [242, 216, 185]},
  {"id": "85", "name": "Sand", "rgb": [227, 194, 152]},
  {"id": "86", "name": "Fawn", "rgb": [207, 171, 131]},
  {"id": "85-Tan", "name": "Tan", "rgb": [197, 148, 99]},
  {"id": "84-LB", "name": "Light Brown", "rgb": [155, 101, 62]},
  {"id": "83-GB", "name": "Gingerbread", "rgb": [121, 76, 41]},
  {"id": "84-Br", "name": "Brown", "rgb": [78, 49, 37]},
  {"id": "85-Co", "name": "Cocoa", "rgb": [55, 34, 28]}
]